{
  "window_days": 7,
  "as_of_today": "2026-07-01",
  "as_of_baseline": "2026-06-24",
  "top_added": [
    {
      "stock_id": "2327",
      "stock_name": "國巨*",
      "etf_count": 4,
      "total_delta": 3.557
    },
    {
      "stock_id": "3037",
      "stock_name": "欣興",
      "etf_count": 5,
      "total_delta": 2.763
    },
    {
      "stock_id": "8046",
      "stock_name": "南電",
      "etf_count": 3,
      "total_delta": 1.688
    },
    {
      "stock_id": "4958",
      "stock_name": "臻鼎-KY",
      "etf_count": 1,
      "total_delta": 1.475
    },
    {
      "stock_id": "3653",
      "stock_name": "健策",
      "etf_count": 2,
      "total_delta": 1.47
    }
  ],
  "top_removed": [
    {
      "stock_id": "6223",
      "stock_name": "旺矽",
      "etf_count": 6,
      "total_delta": -2.101
    },
    {
      "stock_id": "5274",
      "stock_name": "信驊",
      "etf_count": 3,
      "total_delta": -1.872
    },
    {
      "stock_id": "8299",
      "stock_name": "群聯電子",
      "etf_count": 2,
      "total_delta": -1.703
    },
    {
      "stock_id": "2344",
      "stock_name": "華邦電",
      "etf_count": 3,
      "total_delta": -1.141
    },
    {
      "stock_id": "2360",
      "stock_name": "致茂",
      "etf_count": 3,
      "total_delta": -1.06
    }
  ]
}