{
  "window_days": 7,
  "as_of_today": "2026-07-07",
  "as_of_baseline": "2026-06-30",
  "top_added": [
    {
      "stock_id": "2330",
      "stock_name": "台積電",
      "etf_count": 7,
      "total_delta": 4.765
    },
    {
      "stock_id": "3017",
      "stock_name": "奇鋐",
      "etf_count": 3,
      "total_delta": 2.812
    },
    {
      "stock_id": "2383",
      "stock_name": "台光電",
      "etf_count": 4,
      "total_delta": 2.773
    },
    {
      "stock_id": "6223",
      "stock_name": "旺矽",
      "etf_count": 6,
      "total_delta": 2.764
    },
    {
      "stock_id": "6669",
      "stock_name": "緯穎",
      "etf_count": 3,
      "total_delta": 2.029
    }
  ],
  "top_removed": [
    {
      "stock_id": "2327",
      "stock_name": "國巨*",
      "etf_count": 4,
      "total_delta": -4.047
    },
    {
      "stock_id": "3037",
      "stock_name": "欣興",
      "etf_count": 5,
      "total_delta": -3.413
    },
    {
      "stock_id": "8996",
      "stock_name": "高力",
      "etf_count": 3,
      "total_delta": -1.973
    },
    {
      "stock_id": "4958",
      "stock_name": "臻鼎-KY",
      "etf_count": 4,
      "total_delta": -1.905
    },
    {
      "stock_id": "2344",
      "stock_name": "華邦電",
      "etf_count": 3,
      "total_delta": -1.438
    }
  ]
}