{
  "window_days": 7,
  "as_of_today": "2026-05-15",
  "as_of_baseline": "2026-05-08",
  "top_added": [
    {
      "stock_id": "6223",
      "stock_name": "旺矽科技",
      "etf_count": 4,
      "total_delta": 5.317
    },
    {
      "stock_id": "2059",
      "stock_name": "川湖科技",
      "etf_count": 2,
      "total_delta": 3.118
    },
    {
      "stock_id": "8210",
      "stock_name": "勤誠興業",
      "etf_count": 3,
      "total_delta": 2.26
    },
    {
      "stock_id": "8996",
      "stock_name": "高力熱處理工業",
      "etf_count": 3,
      "total_delta": 2.165
    },
    {
      "stock_id": "2345",
      "stock_name": "智邦科技",
      "etf_count": 5,
      "total_delta": 2.079
    }
  ],
  "top_removed": [
    {
      "stock_id": "3665",
      "stock_name": "貿聯控股（BizLink Holding In",
      "etf_count": 4,
      "total_delta": -7.728
    },
    {
      "stock_id": "6139",
      "stock_name": "亞翔",
      "etf_count": 1,
      "total_delta": -3.86
    },
    {
      "stock_id": "2454",
      "stock_name": "聯發科技",
      "etf_count": 5,
      "total_delta": -3.119
    },
    {
      "stock_id": "2308",
      "stock_name": "台達電子工業",
      "etf_count": 5,
      "total_delta": -2.328
    },
    {
      "stock_id": "2330",
      "stock_name": "台灣積體電路製造",
      "etf_count": 5,
      "total_delta": -2.212
    }
  ]
}