{"date": "2026-06-03", "source": "finmind", "fetched_at": "2026-06-03T18:31:36+08:00", "prices": {"1216": {"close": 73.3, "change": -0.9, "change_pct": -1.21, "exchange": "TWSE"}, "1301": {"close": 52.0, "change": 1.1, "change_pct": 2.16, "exchange": "TWSE"}, "1303": {"close": 113.0, "change": 0.5, "change_pct": 0.44, "exchange": "TWSE"}, "1319": {"close": 94.3, "change": 2.2, "change_pct": 2.39, "exchange": "TWSE"}, "1519": {"close": 935.0, "change": 85.0, "change_pct": 10.0, "exchange": "TWSE"}, "1590": {"close": 1370.0, "change": 90.0, "change_pct": 7.03, "exchange": "TWSE"}, "1815": {"close": 106.5, "change": -3.0, "change_pct": -2.74, "exchange": "TWSE"}, "2002": {"close": 19.4, "change": 0.45, "change_pct": 2.37, "exchange": "TWSE"}, "2059": {"close": 5350.0, "change": 275.0, "change_pct": 5.42, "exchange": "TWSE"}, "2207": {"close": 485.0, "change": 13.5, "change_pct": 2.86, "exchange": "TWSE"}, "2301": {"close": 250.0, "change": 22.5, "change_pct": 9.89, "exchange": "TWSE"}, "2303": {"close": 130.5, "change": -11.0, "change_pct": -7.77, "exchange": "TWSE"}, "2308": {"close": 2455.0, "change": 95.0, "change_pct": 4.03, "exchange": "TWSE"}, "2313": {"close": 266.5, "change": -4.0, "change_pct": -1.48, "exchange": "TWSE"}, "2317": {"close": 309.0, "change": 7.5, "change_pct": 2.49, "exchange": "TWSE"}, "2327": {"close": 820.0, "change": -26.0, "change_pct": -3.07, "exchange": "TWSE"}, "2330": {"close": 2425.0, "change": 45.0, "change_pct": 1.89, "exchange": "TWSE"}, "2337": {"close": 162.0, "change": -13.5, "change_pct": -7.69, "exchange": "TWSE"}, "2344": {"close": 177.5, "change": -7.0, "change_pct": -3.79, "exchange": "TWSE"}, "2345": {"close": 2585.0, "change": 160.0, "change_pct": 6.6, "exchange": "TWSE"}, "2357": {"close": 931.0, "change": 11.0, "change_pct": 1.2, "exchange": "TWSE"}, "2360": {"close": 2545.0, "change": 125.0, "change_pct": 5.17, "exchange": "TWSE"}, "2368": {"close": 1385.0, "change": 110.0, "change_pct": 8.63, "exchange": "TWSE"}, "2376": {"close": 399.0, "change": 8.5, "change_pct": 2.18, "exchange": "TWSE"}, "2382": {"close": 417.0, "change": 16.5, "change_pct": 4.12, "exchange": "TWSE"}, "2383": {"close": 4830.0, "change": -30.0, "change_pct": -0.62, "exchange": "TWSE"}, "2395": {"close": 513.0, "change": -2.0, "change_pct": -0.39, "exchange": "TWSE"}, "2404": {"close": 1155.0, "change": 5.0, "change_pct": 0.43, "exchange": "TWSE"}, "2408": {"close": 401.5, "change": -18.0, "change_pct": -4.29, "exchange": "TWSE"}, "2412": {"close": 141.0, "change": -1.0, "change_pct": -0.7, "exchange": "TWSE"}, "2439": {"close": 94.0, "change": 0.5, "change_pct": 0.53, "exchange": "TWSE"}, "2449": {"close": 322.5, "change": 16.0, "change_pct": 5.22, "exchange": "TWSE"}, "2454": {"close": 4545.0, "change": 20.0, "change_pct": 0.44, "exchange": "TWSE"}, "2481": {"close": 159.0, "change": 13.0, "change_pct": 8.9, "exchange": "TWSE"}, "2603": {"close": 237.0, "change": 6.0, "change_pct": 2.6, "exchange": "TWSE"}, "2880": {"close": 36.4, "change": 2.35, "change_pct": 6.9, "exchange": "TWSE"}, "2881": {"close": 113.0, "change": -0.5, "change_pct": -0.44, "exchange": "TWSE"}, "2882": {"close": 91.8, "change": 2.6, "change_pct": 2.91, "exchange": "TWSE"}, "2883": {"close": 25.7, "change": 2.3, "change_pct": 9.83, "exchange": "TWSE"}, "2884": {"close": 33.0, "change": 0.8, "change_pct": 2.48, "exchange": "TWSE"}, "2885": {"close": 63.7, "change": 4.1, "change_pct": 6.88, "exchange": "TWSE"}, "2886": {"close": 41.65, "change": -0.05, "change_pct": -0.12, "exchange": "TWSE"}, "2887": {"close": 28.3, "change": 2.2, "change_pct": 8.43, "exchange": "TWSE"}, "2890": {"close": 33.0, "change": 2.0, "change_pct": 6.45, "exchange": "TWSE"}, "2891": {"close": 70.5, "change": 6.4, "change_pct": 9.98, "exchange": "TWSE"}, "2892": {"close": 29.0, "change": 0.85, "change_pct": 3.02, "exchange": "TWSE"}, "3008": {"close": 3985.0, "change": 135.0, "change_pct": 3.51, "exchange": "TWSE"}, "3017": {"close": 2855.0, "change": 155.0, "change_pct": 5.74, "exchange": "TWSE"}, "3036": {"close": 292.5, "change": 2.0, "change_pct": 0.69, "exchange": "TWSE"}, "3037": {"close": 1000.0, "change": 25.0, "change_pct": 2.56, "exchange": "TWSE"}, "3042": {"close": 217.5, "change": 7.5, "change_pct": 3.57, "exchange": "TWSE"}, "3044": {"close": 510.0, "change": 2.0, "change_pct": 0.39, "exchange": "TWSE"}, "3045": {"close": 116.0, "change": 0.5, "change_pct": 0.43, "exchange": "TWSE"}, "3081": {"close": 2830.0, "change": 255.0, "change_pct": 9.9, "exchange": "TWSE"}, "3105": {"close": 515.0, "change": -4.0, "change_pct": -0.77, "exchange": "TWSE"}, "3189": {"close": 739.0, "change": -4.0, "change_pct": -0.54, "exchange": "TWSE"}, "3231": {"close": 194.0, "change": 3.0, "change_pct": 1.57, "exchange": "TWSE"}, "3264": {"close": 229.5, "change": 15.0, "change_pct": 6.99, "exchange": "TWSE"}, "3293": {"close": 789.0, "change": -10.0, "change_pct": -1.25, "exchange": "TWSE"}, "3324": {"close": 1280.0, "change": 115.0, "change_pct": 9.87, "exchange": "TWSE"}, "3376": {"close": 226.5, "change": 15.0, "change_pct": 7.09, "exchange": "TWSE"}, "3443": {"close": 4605.0, "change": 70.0, "change_pct": 1.54, "exchange": "TWSE"}, "3491": {"close": 2020.0, "change": -50.0, "change_pct": -2.42, "exchange": "TWSE"}, "3529": {"close": 3570.0, "change": 40.0, "change_pct": 1.13, "exchange": "TWSE"}, "3533": {"close": 2570.0, "change": -45.0, "change_pct": -1.72, "exchange": "TWSE"}, "3653": {"close": 3905.0, "change": -85.0, "change_pct": -2.13, "exchange": "TWSE"}, "3661": {"close": 4595.0, "change": 20.0, "change_pct": 0.44, "exchange": "TWSE"}, "3665": {"close": 2305.0, "change": 110.0, "change_pct": 5.01, "exchange": "TWSE"}, "3711": {"close": 618.0, "change": 28.0, "change_pct": 4.75, "exchange": "TWSE"}, "4904": {"close": 100.5, "change": 1.0, "change_pct": 1.01, "exchange": "TWSE"}, "4958": {"close": 510.0, "change": -10.0, "change_pct": -1.92, "exchange": "TWSE"}, "4966": {"close": 805.0, "change": -22.0, "change_pct": -2.66, "exchange": "TWSE"}, "5274": {"close": 17980.0, "change": -115.0, "change_pct": -0.64, "exchange": "TWSE"}, "5347": {"close": 168.0, "change": -3.5, "change_pct": -2.04, "exchange": "TWSE"}, "5439": {"close": 375.0, "change": 1.0, "change_pct": 0.27, "exchange": "TWSE"}, "5536": {"close": 1055.0, "change": 57.0, "change_pct": 5.71, "exchange": "TWSE"}, "5880": {"close": 23.4, "change": 0.35, "change_pct": 1.52, "exchange": "TWSE"}, "5904": {"close": 571.0, "change": 3.0, "change_pct": 0.53, "exchange": "TWSE"}, "6139": {"close": 784.0, "change": 22.0, "change_pct": 2.89, "exchange": "TWSE"}, "6147": {"close": 275.0, "change": -6.0, "change_pct": -2.14, "exchange": "TWSE"}, "6187": {"close": 1065.0, "change": 55.0, "change_pct": 5.45, "exchange": "TWSE"}, "6191": {"close": 100.5, "change": 3.5, "change_pct": 3.61, "exchange": "TWSE"}, "6223": {"close": 5900.0, "change": 385.0, "change_pct": 6.98, "exchange": "TWSE"}, "6271": {"close": 250.0, "change": 0.5, "change_pct": 0.2, "exchange": "TWSE"}, "6274": {"close": 1695.0, "change": 105.0, "change_pct": 6.6, "exchange": "TWSE"}, "6278": {"close": 209.0, "change": -5.5, "change_pct": -2.56, "exchange": "TWSE"}, "6442": {"close": 2065.0, "change": 185.0, "change_pct": 9.84, "exchange": "TWSE"}, "6505": {"close": 55.9, "change": 1.4, "change_pct": 2.57, "exchange": "TWSE"}, "6510": {"close": 3310.0, "change": 95.0, "change_pct": 2.95, "exchange": "TWSE"}, "6515": {"close": 8220.0, "change": 140.0, "change_pct": 1.73, "exchange": "TWSE"}, "6669": {"close": 5600.0, "change": 125.0, "change_pct": 2.28, "exchange": "TWSE"}, "6805": {"close": 2085.0, "change": -105.0, "change_pct": -4.79, "exchange": "TWSE"}, "6831": {"close": 726.0, "change": 40.0, "change_pct": 5.83, "exchange": "TWSE"}, "6919": {"close": 96.5, "change": -0.3, "change_pct": -0.31, "exchange": "TWSE"}, "7769": {"close": 7525.0, "change": 350.0, "change_pct": 4.88, "exchange": "TWSE"}, "8046": {"close": 904.0, "change": 42.0, "change_pct": 4.87, "exchange": "TWSE"}, "8150": {"close": 95.8, "change": -2.8, "change_pct": -2.84, "exchange": "TWSE"}, "8210": {"close": 1455.0, "change": 80.0, "change_pct": 5.82, "exchange": "TWSE"}, "8299": {"close": 2685.0, "change": -135.0, "change_pct": -4.79, "exchange": "TWSE"}, "8358": {"close": 615.0, "change": -12.0, "change_pct": -1.91, "exchange": "TWSE"}, "8996": {"close": 1095.0, "change": 45.0, "change_pct": 4.29, "exchange": "TWSE"}}, "missing": []}